MANIFEST.in
Readme.md
dev-requirements.txt
licence.txt
requirements.txt
setup.cfg
setup.py
pandas_ml_quant_rl/__init__.py
pandas_ml_quant_rl.egg-info/PKG-INFO
pandas_ml_quant_rl.egg-info/SOURCES.txt
pandas_ml_quant_rl.egg-info/dependency_links.txt
pandas_ml_quant_rl.egg-info/requires.txt
pandas_ml_quant_rl.egg-info/top_level.txt
pandas_ml_quant_rl/__pycache__/__init__.cpython-37.pyc
pandas_ml_quant_rl/__pycache__/__init__.cpython-38.pyc
pandas_ml_quant_rl/buffer/__init__.py
pandas_ml_quant_rl/buffer/abstract_buffer.py
pandas_ml_quant_rl/buffer/list_buffer.py
pandas_ml_quant_rl/buffer/__pycache__/__init__.cpython-37.pyc
pandas_ml_quant_rl/buffer/__pycache__/__init__.cpython-38.pyc
pandas_ml_quant_rl/buffer/__pycache__/abstract_buffer.cpython-37.pyc
pandas_ml_quant_rl/buffer/__pycache__/abstract_buffer.cpython-38.pyc
pandas_ml_quant_rl/buffer/__pycache__/list_buffer.cpython-37.pyc
pandas_ml_quant_rl/buffer/__pycache__/list_buffer.cpython-38.pyc
pandas_ml_quant_rl/cache/__init__.py
pandas_ml_quant_rl/cache/abstract_cache.py
pandas_ml_quant_rl/cache/file_cache.py
pandas_ml_quant_rl/cache/mem_cache.py
pandas_ml_quant_rl/cache/no_cache.py
pandas_ml_quant_rl/cache/__pycache__/__init__.cpython-37.pyc
pandas_ml_quant_rl/cache/__pycache__/__init__.cpython-38.pyc
pandas_ml_quant_rl/cache/__pycache__/abstract_cache.cpython-37.pyc
pandas_ml_quant_rl/cache/__pycache__/abstract_cache.cpython-38.pyc
pandas_ml_quant_rl/cache/__pycache__/file_cache.cpython-37.pyc
pandas_ml_quant_rl/cache/__pycache__/file_cache.cpython-38.pyc
pandas_ml_quant_rl/cache/__pycache__/mem_cache.cpython-37.pyc
pandas_ml_quant_rl/cache/__pycache__/mem_cache.cpython-38.pyc
pandas_ml_quant_rl/cache/__pycache__/no_cache.cpython-37.pyc
pandas_ml_quant_rl/cache/__pycache__/no_cache.cpython-38.pyc
pandas_ml_quant_rl/environments/__init__.py
pandas_ml_quant_rl/environments/cart_pole_environment.py
pandas_ml_quant_rl/environments/multi_symbol_environment.py
pandas_ml_quant_rl/environments/utils.py
pandas_ml_quant_rl/environments/__pycache__/__init__.cpython-37.pyc
pandas_ml_quant_rl/environments/__pycache__/__init__.cpython-38.pyc
pandas_ml_quant_rl/environments/__pycache__/cart_pole_environment.cpython-37.pyc
